<profile>

<RTLDesignHierarchy>
<TopModule>
<ModuleName>knn_cluster2</ModuleName>
<InstancesList>
<Instance>
<InstName>update_knn10_U0</InstName>
<ModuleName>update_knn10</ModuleName>
<IsCompInst>true</IsCompInst>
<ID>152</ID>
<InstancesList>
<Instance>
<InstName>grp_popcount_fu_347</InstName>
<ModuleName>popcount</ModuleName>
<IsCompInst>true</IsCompInst>
<ID>347</ID>
</Instance>
</InstancesList>
</Instance>
<Instance>
<InstName>update_knn6_U0</InstName>
<ModuleName>update_knn6</ModuleName>
<IsCompInst>true</IsCompInst>
<ID>175</ID>
<InstancesList>
<Instance>
<InstName>grp_popcount_fu_345</InstName>
<ModuleName>popcount</ModuleName>
<IsCompInst>true</IsCompInst>
<ID>345</ID>
</Instance>
</InstancesList>
</Instance>
<Instance>
<InstName>update_knn7_U0</InstName>
<ModuleName>update_knn7</ModuleName>
<IsCompInst>true</IsCompInst>
<ID>198</ID>
<InstancesList>
<Instance>
<InstName>grp_popcount_fu_347</InstName>
<ModuleName>popcount</ModuleName>
<IsCompInst>true</IsCompInst>
<ID>347</ID>
</Instance>
</InstancesList>
</Instance>
<Instance>
<InstName>update_knn8_U0</InstName>
<ModuleName>update_knn8</ModuleName>
<IsCompInst>true</IsCompInst>
<ID>220</ID>
<InstancesList>
<Instance>
<InstName>grp_popcount_fu_347</InstName>
<ModuleName>popcount</ModuleName>
<IsCompInst>true</IsCompInst>
<ID>347</ID>
</Instance>
</InstancesList>
</Instance>
<Instance>
<InstName>update_knn9_U0</InstName>
<ModuleName>update_knn9</ModuleName>
<IsCompInst>true</IsCompInst>
<ID>242</ID>
<InstancesList>
<Instance>
<InstName>grp_popcount_fu_347</InstName>
<ModuleName>popcount</ModuleName>
<IsCompInst>true</IsCompInst>
<ID>347</ID>
</Instance>
</InstancesList>
</Instance>
</InstancesList>
</TopModule>
</RTLDesignHierarchy>

<ModuleInformation>
<Module>
<Name>popcount</Name>
<PerformanceEstimates>
<SummaryOfTimingAnalysis>
<TargetClockPeriod>10.00</TargetClockPeriod>
<ClockUncertainty>1.25</ClockUncertainty>
<TargetInitiationInterval>4294967295</TargetInitiationInterval>
<EstimatedClockPeriod>8.677</EstimatedClockPeriod>
</SummaryOfTimingAnalysis>
<SummaryOfOverallLatency>
<Best-caseLatency>6</Best-caseLatency>
<Average-caseLatency>6</Average-caseLatency>
<Worst-caseLatency>6</Worst-caseLatency>
<Best-caseRealTimeLatency>60.000 ns</Best-caseRealTimeLatency>
<Average-caseRealTimeLatency>60.000 ns</Average-caseRealTimeLatency>
<Worst-caseRealTimeLatency>60.000 ns</Worst-caseRealTimeLatency>
<PipelineInitiationInterval>1</PipelineInitiationInterval>
<PipelineDepth>7</PipelineDepth>
<PipelineType>function</PipelineType>
</SummaryOfOverallLatency>
</PerformanceEstimates>
<AreaEstimates>
<Resources>
<BRAM_18K>0</BRAM_18K>
<FF>1364</FF>
<LUT>2555</LUT>
<DSP48E>0</DSP48E>
<URAM>0</URAM>
</Resources>
</AreaEstimates>
<InterfaceSummary>
<RtlPorts>
<name>ap_clk</name>
<Object>popcount</Object>
<Type>return value</Type>
<Scope></Scope>
<IOProtocol>ap_ctrl_hs</IOProtocol>
<IOConfig></IOConfig>
<Dir>in</Dir>
<Bits>1</Bits>
<Attribute>control</Attribute>
</RtlPorts>
<RtlPorts>
<name>ap_rst</name>
<Object>popcount</Object>
<Type>return value</Type>
<Scope></Scope>
<IOProtocol>ap_ctrl_hs</IOProtocol>
<IOConfig></IOConfig>
<Dir>in</Dir>
<Bits>1</Bits>
<Attribute>control</Attribute>
</RtlPorts>
<RtlPorts>
<name>ap_return</name>
<Object>popcount</Object>
<Type>return value</Type>
<Scope></Scope>
<IOProtocol>ap_ctrl_hs</IOProtocol>
<IOConfig></IOConfig>
<Dir>out</Dir>
<Bits>8</Bits>
<Attribute>data</Attribute>
</RtlPorts>
<RtlPorts>
<name>x_V</name>
<Object>x_V</Object>
<Type>scalar</Type>
<Scope></Scope>
<IOProtocol>ap_none</IOProtocol>
<IOConfig></IOConfig>
<Dir>in</Dir>
<Bits>196</Bits>
<Attribute>data</Attribute>
</RtlPorts>
</InterfaceSummary>
</Module>
<Module>
<Name>update_knn6</Name>
<PerformanceEstimates>
<SummaryOfTimingAnalysis>
<TargetClockPeriod>10.00</TargetClockPeriod>
<ClockUncertainty>1.25</ClockUncertainty>
<EstimatedClockPeriod>8.677</EstimatedClockPeriod>
</SummaryOfTimingAnalysis>
<SummaryOfOverallLatency>
<Best-caseLatency>493</Best-caseLatency>
<Average-caseLatency>27495</Average-caseLatency>
<Worst-caseLatency>54496</Worst-caseLatency>
<Best-caseRealTimeLatency>4.930 us</Best-caseRealTimeLatency>
<Average-caseRealTimeLatency>0.275 ms</Average-caseRealTimeLatency>
<Worst-caseRealTimeLatency>0.545 ms</Worst-caseRealTimeLatency>
<PipelineInitiationInterval>493 ~ 54496</PipelineInitiationInterval>
<PipelineType>none</PipelineType>
</SummaryOfOverallLatency>
<SummaryOfLoopLatency>
<STORE_LOCAL>
<Name>STORE_LOCAL</Name>
<TripCount>450</TripCount>
<Latency>3600</Latency>
<PipelineII>8</PipelineII>
<PipelineDepth>8</PipelineDepth>
</STORE_LOCAL>
<TRANSFER_LOOP>
<Name>TRANSFER_LOOP</Name>
<TripCount>6300</TripCount>
<Latency>50400</Latency>
<PipelineII>8</PipelineII>
<PipelineDepth>9</PipelineDepth>
</TRANSFER_LOOP>
<TRAINING_LOOP_LANES>
<Name>TRAINING_LOOP_LANES</Name>
<TripCount>450</TripCount>
<Latency>460</Latency>
<PipelineII>1</PipelineII>
<PipelineDepth>12</PipelineDepth>
</TRAINING_LOOP_LANES>
<LANES_INSERTION_SORT_OUTER>
<Name>LANES_INSERTION_SORT_OUTER</Name>
<TripCount>6</TripCount>
<Latency>6</Latency>
<PipelineII>1</PipelineII>
<PipelineDepth>2</PipelineDepth>
</LANES_INSERTION_SORT_OUTER>
</SummaryOfLoopLatency>
</PerformanceEstimates>
<AreaEstimates>
<Resources>
<BRAM_18K>8</BRAM_18K>
<DSP48E>1</DSP48E>
<FF>2787</FF>
<LUT>4434</LUT>
<URAM>0</URAM>
</Resources>
</AreaEstimates>
<InterfaceSummary>
<RtlPorts>
<name>ap_clk</name>
<Object>update_knn6</Object>
<Type>return value</Type>
<Scope></Scope>
<IOProtocol>ap_ctrl_hs</IOProtocol>
<IOConfig></IOConfig>
<Dir>in</Dir>
<Bits>1</Bits>
<Attribute>control</Attribute>
</RtlPorts>
<RtlPorts>
<name>ap_rst</name>
<Object>update_knn6</Object>
<Type>return value</Type>
<Scope></Scope>
<IOProtocol>ap_ctrl_hs</IOProtocol>
<IOConfig></IOConfig>
<Dir>in</Dir>
<Bits>1</Bits>
<Attribute>control</Attribute>
</RtlPorts>
<RtlPorts>
<name>ap_start</name>
<Object>update_knn6</Object>
<Type>return value</Type>
<Scope></Scope>
<IOProtocol>ap_ctrl_hs</IOProtocol>
<IOConfig></IOConfig>
<Dir>in</Dir>
<Bits>1</Bits>
<Attribute>control</Attribute>
</RtlPorts>
<RtlPorts>
<name>start_full_n</name>
<Object>update_knn6</Object>
<Type>return value</Type>
<Scope></Scope>
<IOProtocol>ap_ctrl_hs</IOProtocol>
<IOConfig></IOConfig>
<Dir>in</Dir>
<Bits>1</Bits>
<Attribute>unknown</Attribute>
</RtlPorts>
<RtlPorts>
<name>ap_done</name>
<Object>update_knn6</Object>
<Type>return value</Type>
<Scope></Scope>
<IOProtocol>ap_ctrl_hs</IOProtocol>
<IOConfig></IOConfig>
<Dir>out</Dir>
<Bits>1</Bits>
<Attribute>control</Attribute>
</RtlPorts>
<RtlPorts>
<name>ap_continue</name>
<Object>update_knn6</Object>
<Type>return value</Type>
<Scope></Scope>
<IOProtocol>ap_ctrl_hs</IOProtocol>
<IOConfig></IOConfig>
<Dir>in</Dir>
<Bits>1</Bits>
<Attribute>control</Attribute>
</RtlPorts>
<RtlPorts>
<name>ap_idle</name>
<Object>update_knn6</Object>
<Type>return value</Type>
<Scope></Scope>
<IOProtocol>ap_ctrl_hs</IOProtocol>
<IOConfig></IOConfig>
<Dir>out</Dir>
<Bits>1</Bits>
<Attribute>control</Attribute>
</RtlPorts>
<RtlPorts>
<name>ap_ready</name>
<Object>update_knn6</Object>
<Type>return value</Type>
<Scope></Scope>
<IOProtocol>ap_ctrl_hs</IOProtocol>
<IOConfig></IOConfig>
<Dir>out</Dir>
<Bits>1</Bits>
<Attribute>control</Attribute>
</RtlPorts>
<RtlPorts>
<name>start_out</name>
<Object>update_knn6</Object>
<Type>return value</Type>
<Scope></Scope>
<IOProtocol>ap_ctrl_hs</IOProtocol>
<IOConfig></IOConfig>
<Dir>out</Dir>
<Bits>1</Bits>
<Attribute>unknown</Attribute>
</RtlPorts>
<RtlPorts>
<name>start_write</name>
<Object>update_knn6</Object>
<Type>return value</Type>
<Scope></Scope>
<IOProtocol>ap_ctrl_hs</IOProtocol>
<IOConfig></IOConfig>
<Dir>out</Dir>
<Bits>1</Bits>
<Attribute>unknown</Attribute>
</RtlPorts>
<RtlPorts>
<name>Input_1_V_V</name>
<Object>Input_1_V_V</Object>
<Type>pointer</Type>
<Scope></Scope>
<IOProtocol>ap_hs</IOProtocol>
<IOConfig></IOConfig>
<Dir>in</Dir>
<Bits>32</Bits>
<Attribute>data</Attribute>
</RtlPorts>
<RtlPorts>
<name>Input_1_V_V_ap_vld</name>
<Object>Input_1_V_V</Object>
<Type>pointer</Type>
<Scope></Scope>
<IOProtocol>ap_hs</IOProtocol>
<IOConfig></IOConfig>
<Dir>in</Dir>
<Bits>1</Bits>
<Attribute>control</Attribute>
</RtlPorts>
<RtlPorts>
<name>Input_1_V_V_ap_ack</name>
<Object>Input_1_V_V</Object>
<Type>pointer</Type>
<Scope></Scope>
<IOProtocol>ap_hs</IOProtocol>
<IOConfig></IOConfig>
<Dir>out</Dir>
<Bits>1</Bits>
<Attribute>control</Attribute>
</RtlPorts>
<RtlPorts>
<name>Output_1_V_V_din</name>
<Object>Output_1_V_V</Object>
<Type>pointer</Type>
<Scope></Scope>
<IOProtocol>ap_fifo</IOProtocol>
<IOConfig></IOConfig>
<Dir>out</Dir>
<Bits>32</Bits>
<Attribute>control</Attribute>
</RtlPorts>
<RtlPorts>
<name>Output_1_V_V_full_n</name>
<Object>Output_1_V_V</Object>
<Type>pointer</Type>
<Scope></Scope>
<IOProtocol>ap_fifo</IOProtocol>
<IOConfig></IOConfig>
<Dir>in</Dir>
<Bits>1</Bits>
<Attribute>control</Attribute>
</RtlPorts>
<RtlPorts>
<name>Output_1_V_V_write</name>
<Object>Output_1_V_V</Object>
<Type>pointer</Type>
<Scope></Scope>
<IOProtocol>ap_fifo</IOProtocol>
<IOConfig></IOConfig>
<Dir>out</Dir>
<Bits>1</Bits>
<Attribute>control</Attribute>
</RtlPorts>
</InterfaceSummary>
</Module>
<Module>
<Name>update_knn7</Name>
<PerformanceEstimates>
<SummaryOfTimingAnalysis>
<TargetClockPeriod>10.00</TargetClockPeriod>
<ClockUncertainty>1.25</ClockUncertainty>
<EstimatedClockPeriod>8.677</EstimatedClockPeriod>
</SummaryOfTimingAnalysis>
<SummaryOfOverallLatency>
<Best-caseLatency>493</Best-caseLatency>
<Average-caseLatency>25695</Average-caseLatency>
<Worst-caseLatency>50896</Worst-caseLatency>
<Best-caseRealTimeLatency>4.930 us</Best-caseRealTimeLatency>
<Average-caseRealTimeLatency>0.257 ms</Average-caseRealTimeLatency>
<Worst-caseRealTimeLatency>0.509 ms</Worst-caseRealTimeLatency>
<PipelineInitiationInterval>493 ~ 50896</PipelineInitiationInterval>
<PipelineType>none</PipelineType>
</SummaryOfOverallLatency>
<SummaryOfLoopLatency>
<STORE_LOCAL>
<Name>STORE_LOCAL</Name>
<TripCount>450</TripCount>
<Latency>3600</Latency>
<PipelineII>8</PipelineII>
<PipelineDepth>9</PipelineDepth>
</STORE_LOCAL>
<TRANSFER_LOOP>
<Name>TRANSFER_LOOP</Name>
<TripCount>5850</TripCount>
<Latency>46800</Latency>
<PipelineII>8</PipelineII>
<PipelineDepth>9</PipelineDepth>
</TRANSFER_LOOP>
<TRAINING_LOOP_LANES>
<Name>TRAINING_LOOP_LANES</Name>
<TripCount>450</TripCount>
<Latency>460</Latency>
<PipelineII>1</PipelineII>
<PipelineDepth>12</PipelineDepth>
</TRAINING_LOOP_LANES>
<LANES_INSERTION_SORT_OUTER>
<Name>LANES_INSERTION_SORT_OUTER</Name>
<TripCount>6</TripCount>
<Latency>6</Latency>
<PipelineII>1</PipelineII>
<PipelineDepth>2</PipelineDepth>
</LANES_INSERTION_SORT_OUTER>
</SummaryOfLoopLatency>
</PerformanceEstimates>
<AreaEstimates>
<Resources>
<BRAM_18K>8</BRAM_18K>
<DSP48E>1</DSP48E>
<FF>2790</FF>
<LUT>4451</LUT>
<URAM>0</URAM>
</Resources>
</AreaEstimates>
<InterfaceSummary>
<RtlPorts>
<name>ap_clk</name>
<Object>update_knn7</Object>
<Type>return value</Type>
<Scope></Scope>
<IOProtocol>ap_ctrl_hs</IOProtocol>
<IOConfig></IOConfig>
<Dir>in</Dir>
<Bits>1</Bits>
<Attribute>control</Attribute>
</RtlPorts>
<RtlPorts>
<name>ap_rst</name>
<Object>update_knn7</Object>
<Type>return value</Type>
<Scope></Scope>
<IOProtocol>ap_ctrl_hs</IOProtocol>
<IOConfig></IOConfig>
<Dir>in</Dir>
<Bits>1</Bits>
<Attribute>control</Attribute>
</RtlPorts>
<RtlPorts>
<name>ap_start</name>
<Object>update_knn7</Object>
<Type>return value</Type>
<Scope></Scope>
<IOProtocol>ap_ctrl_hs</IOProtocol>
<IOConfig></IOConfig>
<Dir>in</Dir>
<Bits>1</Bits>
<Attribute>control</Attribute>
</RtlPorts>
<RtlPorts>
<name>start_full_n</name>
<Object>update_knn7</Object>
<Type>return value</Type>
<Scope></Scope>
<IOProtocol>ap_ctrl_hs</IOProtocol>
<IOConfig></IOConfig>
<Dir>in</Dir>
<Bits>1</Bits>
<Attribute>unknown</Attribute>
</RtlPorts>
<RtlPorts>
<name>ap_done</name>
<Object>update_knn7</Object>
<Type>return value</Type>
<Scope></Scope>
<IOProtocol>ap_ctrl_hs</IOProtocol>
<IOConfig></IOConfig>
<Dir>out</Dir>
<Bits>1</Bits>
<Attribute>control</Attribute>
</RtlPorts>
<RtlPorts>
<name>ap_continue</name>
<Object>update_knn7</Object>
<Type>return value</Type>
<Scope></Scope>
<IOProtocol>ap_ctrl_hs</IOProtocol>
<IOConfig></IOConfig>
<Dir>in</Dir>
<Bits>1</Bits>
<Attribute>control</Attribute>
</RtlPorts>
<RtlPorts>
<name>ap_idle</name>
<Object>update_knn7</Object>
<Type>return value</Type>
<Scope></Scope>
<IOProtocol>ap_ctrl_hs</IOProtocol>
<IOConfig></IOConfig>
<Dir>out</Dir>
<Bits>1</Bits>
<Attribute>control</Attribute>
</RtlPorts>
<RtlPorts>
<name>ap_ready</name>
<Object>update_knn7</Object>
<Type>return value</Type>
<Scope></Scope>
<IOProtocol>ap_ctrl_hs</IOProtocol>
<IOConfig></IOConfig>
<Dir>out</Dir>
<Bits>1</Bits>
<Attribute>control</Attribute>
</RtlPorts>
<RtlPorts>
<name>start_out</name>
<Object>update_knn7</Object>
<Type>return value</Type>
<Scope></Scope>
<IOProtocol>ap_ctrl_hs</IOProtocol>
<IOConfig></IOConfig>
<Dir>out</Dir>
<Bits>1</Bits>
<Attribute>unknown</Attribute>
</RtlPorts>
<RtlPorts>
<name>start_write</name>
<Object>update_knn7</Object>
<Type>return value</Type>
<Scope></Scope>
<IOProtocol>ap_ctrl_hs</IOProtocol>
<IOConfig></IOConfig>
<Dir>out</Dir>
<Bits>1</Bits>
<Attribute>unknown</Attribute>
</RtlPorts>
<RtlPorts>
<name>Input_1_V_V_dout</name>
<Object>Input_1_V_V</Object>
<Type>pointer</Type>
<Scope></Scope>
<IOProtocol>ap_fifo</IOProtocol>
<IOConfig></IOConfig>
<Dir>in</Dir>
<Bits>32</Bits>
<Attribute>control</Attribute>
</RtlPorts>
<RtlPorts>
<name>Input_1_V_V_empty_n</name>
<Object>Input_1_V_V</Object>
<Type>pointer</Type>
<Scope></Scope>
<IOProtocol>ap_fifo</IOProtocol>
<IOConfig></IOConfig>
<Dir>in</Dir>
<Bits>1</Bits>
<Attribute>control</Attribute>
</RtlPorts>
<RtlPorts>
<name>Input_1_V_V_read</name>
<Object>Input_1_V_V</Object>
<Type>pointer</Type>
<Scope></Scope>
<IOProtocol>ap_fifo</IOProtocol>
<IOConfig></IOConfig>
<Dir>out</Dir>
<Bits>1</Bits>
<Attribute>control</Attribute>
</RtlPorts>
<RtlPorts>
<name>Output_1_V_V_din</name>
<Object>Output_1_V_V</Object>
<Type>pointer</Type>
<Scope></Scope>
<IOProtocol>ap_fifo</IOProtocol>
<IOConfig></IOConfig>
<Dir>out</Dir>
<Bits>32</Bits>
<Attribute>control</Attribute>
</RtlPorts>
<RtlPorts>
<name>Output_1_V_V_full_n</name>
<Object>Output_1_V_V</Object>
<Type>pointer</Type>
<Scope></Scope>
<IOProtocol>ap_fifo</IOProtocol>
<IOConfig></IOConfig>
<Dir>in</Dir>
<Bits>1</Bits>
<Attribute>control</Attribute>
</RtlPorts>
<RtlPorts>
<name>Output_1_V_V_write</name>
<Object>Output_1_V_V</Object>
<Type>pointer</Type>
<Scope></Scope>
<IOProtocol>ap_fifo</IOProtocol>
<IOConfig></IOConfig>
<Dir>out</Dir>
<Bits>1</Bits>
<Attribute>control</Attribute>
</RtlPorts>
</InterfaceSummary>
</Module>
<Module>
<Name>update_knn8</Name>
<PerformanceEstimates>
<SummaryOfTimingAnalysis>
<TargetClockPeriod>10.00</TargetClockPeriod>
<ClockUncertainty>1.25</ClockUncertainty>
<EstimatedClockPeriod>8.677</EstimatedClockPeriod>
</SummaryOfTimingAnalysis>
<SummaryOfOverallLatency>
<Best-caseLatency>493</Best-caseLatency>
<Average-caseLatency>23895</Average-caseLatency>
<Worst-caseLatency>47296</Worst-caseLatency>
<Best-caseRealTimeLatency>4.930 us</Best-caseRealTimeLatency>
<Average-caseRealTimeLatency>0.239 ms</Average-caseRealTimeLatency>
<Worst-caseRealTimeLatency>0.473 ms</Worst-caseRealTimeLatency>
<PipelineInitiationInterval>493 ~ 47296</PipelineInitiationInterval>
<PipelineType>none</PipelineType>
</SummaryOfOverallLatency>
<SummaryOfLoopLatency>
<STORE_LOCAL>
<Name>STORE_LOCAL</Name>
<TripCount>450</TripCount>
<Latency>3600</Latency>
<PipelineII>8</PipelineII>
<PipelineDepth>9</PipelineDepth>
</STORE_LOCAL>
<TRANSFER_LOOP>
<Name>TRANSFER_LOOP</Name>
<TripCount>5400</TripCount>
<Latency>43200</Latency>
<PipelineII>8</PipelineII>
<PipelineDepth>9</PipelineDepth>
</TRANSFER_LOOP>
<TRAINING_LOOP_LANES>
<Name>TRAINING_LOOP_LANES</Name>
<TripCount>450</TripCount>
<Latency>460</Latency>
<PipelineII>1</PipelineII>
<PipelineDepth>12</PipelineDepth>
</TRAINING_LOOP_LANES>
<LANES_INSERTION_SORT_OUTER>
<Name>LANES_INSERTION_SORT_OUTER</Name>
<TripCount>6</TripCount>
<Latency>6</Latency>
<PipelineII>1</PipelineII>
<PipelineDepth>2</PipelineDepth>
</LANES_INSERTION_SORT_OUTER>
</SummaryOfLoopLatency>
</PerformanceEstimates>
<AreaEstimates>
<Resources>
<BRAM_18K>8</BRAM_18K>
<DSP48E>1</DSP48E>
<FF>2790</FF>
<LUT>4451</LUT>
<URAM>0</URAM>
</Resources>
</AreaEstimates>
<InterfaceSummary>
<RtlPorts>
<name>ap_clk</name>
<Object>update_knn8</Object>
<Type>return value</Type>
<Scope></Scope>
<IOProtocol>ap_ctrl_hs</IOProtocol>
<IOConfig></IOConfig>
<Dir>in</Dir>
<Bits>1</Bits>
<Attribute>control</Attribute>
</RtlPorts>
<RtlPorts>
<name>ap_rst</name>
<Object>update_knn8</Object>
<Type>return value</Type>
<Scope></Scope>
<IOProtocol>ap_ctrl_hs</IOProtocol>
<IOConfig></IOConfig>
<Dir>in</Dir>
<Bits>1</Bits>
<Attribute>control</Attribute>
</RtlPorts>
<RtlPorts>
<name>ap_start</name>
<Object>update_knn8</Object>
<Type>return value</Type>
<Scope></Scope>
<IOProtocol>ap_ctrl_hs</IOProtocol>
<IOConfig></IOConfig>
<Dir>in</Dir>
<Bits>1</Bits>
<Attribute>control</Attribute>
</RtlPorts>
<RtlPorts>
<name>start_full_n</name>
<Object>update_knn8</Object>
<Type>return value</Type>
<Scope></Scope>
<IOProtocol>ap_ctrl_hs</IOProtocol>
<IOConfig></IOConfig>
<Dir>in</Dir>
<Bits>1</Bits>
<Attribute>unknown</Attribute>
</RtlPorts>
<RtlPorts>
<name>ap_done</name>
<Object>update_knn8</Object>
<Type>return value</Type>
<Scope></Scope>
<IOProtocol>ap_ctrl_hs</IOProtocol>
<IOConfig></IOConfig>
<Dir>out</Dir>
<Bits>1</Bits>
<Attribute>control</Attribute>
</RtlPorts>
<RtlPorts>
<name>ap_continue</name>
<Object>update_knn8</Object>
<Type>return value</Type>
<Scope></Scope>
<IOProtocol>ap_ctrl_hs</IOProtocol>
<IOConfig></IOConfig>
<Dir>in</Dir>
<Bits>1</Bits>
<Attribute>control</Attribute>
</RtlPorts>
<RtlPorts>
<name>ap_idle</name>
<Object>update_knn8</Object>
<Type>return value</Type>
<Scope></Scope>
<IOProtocol>ap_ctrl_hs</IOProtocol>
<IOConfig></IOConfig>
<Dir>out</Dir>
<Bits>1</Bits>
<Attribute>control</Attribute>
</RtlPorts>
<RtlPorts>
<name>ap_ready</name>
<Object>update_knn8</Object>
<Type>return value</Type>
<Scope></Scope>
<IOProtocol>ap_ctrl_hs</IOProtocol>
<IOConfig></IOConfig>
<Dir>out</Dir>
<Bits>1</Bits>
<Attribute>control</Attribute>
</RtlPorts>
<RtlPorts>
<name>start_out</name>
<Object>update_knn8</Object>
<Type>return value</Type>
<Scope></Scope>
<IOProtocol>ap_ctrl_hs</IOProtocol>
<IOConfig></IOConfig>
<Dir>out</Dir>
<Bits>1</Bits>
<Attribute>unknown</Attribute>
</RtlPorts>
<RtlPorts>
<name>start_write</name>
<Object>update_knn8</Object>
<Type>return value</Type>
<Scope></Scope>
<IOProtocol>ap_ctrl_hs</IOProtocol>
<IOConfig></IOConfig>
<Dir>out</Dir>
<Bits>1</Bits>
<Attribute>unknown</Attribute>
</RtlPorts>
<RtlPorts>
<name>Input_1_V_V_dout</name>
<Object>Input_1_V_V</Object>
<Type>pointer</Type>
<Scope></Scope>
<IOProtocol>ap_fifo</IOProtocol>
<IOConfig></IOConfig>
<Dir>in</Dir>
<Bits>32</Bits>
<Attribute>control</Attribute>
</RtlPorts>
<RtlPorts>
<name>Input_1_V_V_empty_n</name>
<Object>Input_1_V_V</Object>
<Type>pointer</Type>
<Scope></Scope>
<IOProtocol>ap_fifo</IOProtocol>
<IOConfig></IOConfig>
<Dir>in</Dir>
<Bits>1</Bits>
<Attribute>control</Attribute>
</RtlPorts>
<RtlPorts>
<name>Input_1_V_V_read</name>
<Object>Input_1_V_V</Object>
<Type>pointer</Type>
<Scope></Scope>
<IOProtocol>ap_fifo</IOProtocol>
<IOConfig></IOConfig>
<Dir>out</Dir>
<Bits>1</Bits>
<Attribute>control</Attribute>
</RtlPorts>
<RtlPorts>
<name>Output_1_V_V_din</name>
<Object>Output_1_V_V</Object>
<Type>pointer</Type>
<Scope></Scope>
<IOProtocol>ap_fifo</IOProtocol>
<IOConfig></IOConfig>
<Dir>out</Dir>
<Bits>32</Bits>
<Attribute>control</Attribute>
</RtlPorts>
<RtlPorts>
<name>Output_1_V_V_full_n</name>
<Object>Output_1_V_V</Object>
<Type>pointer</Type>
<Scope></Scope>
<IOProtocol>ap_fifo</IOProtocol>
<IOConfig></IOConfig>
<Dir>in</Dir>
<Bits>1</Bits>
<Attribute>control</Attribute>
</RtlPorts>
<RtlPorts>
<name>Output_1_V_V_write</name>
<Object>Output_1_V_V</Object>
<Type>pointer</Type>
<Scope></Scope>
<IOProtocol>ap_fifo</IOProtocol>
<IOConfig></IOConfig>
<Dir>out</Dir>
<Bits>1</Bits>
<Attribute>control</Attribute>
</RtlPorts>
</InterfaceSummary>
</Module>
<Module>
<Name>update_knn9</Name>
<PerformanceEstimates>
<SummaryOfTimingAnalysis>
<TargetClockPeriod>10.00</TargetClockPeriod>
<ClockUncertainty>1.25</ClockUncertainty>
<EstimatedClockPeriod>8.677</EstimatedClockPeriod>
</SummaryOfTimingAnalysis>
<SummaryOfOverallLatency>
<Best-caseLatency>493</Best-caseLatency>
<Average-caseLatency>22095</Average-caseLatency>
<Worst-caseLatency>43696</Worst-caseLatency>
<Best-caseRealTimeLatency>4.930 us</Best-caseRealTimeLatency>
<Average-caseRealTimeLatency>0.221 ms</Average-caseRealTimeLatency>
<Worst-caseRealTimeLatency>0.437 ms</Worst-caseRealTimeLatency>
<PipelineInitiationInterval>493 ~ 43696</PipelineInitiationInterval>
<PipelineType>none</PipelineType>
</SummaryOfOverallLatency>
<SummaryOfLoopLatency>
<STORE_LOCAL>
<Name>STORE_LOCAL</Name>
<TripCount>450</TripCount>
<Latency>3600</Latency>
<PipelineII>8</PipelineII>
<PipelineDepth>9</PipelineDepth>
</STORE_LOCAL>
<TRANSFER_LOOP>
<Name>TRANSFER_LOOP</Name>
<TripCount>4950</TripCount>
<Latency>39600</Latency>
<PipelineII>8</PipelineII>
<PipelineDepth>9</PipelineDepth>
</TRANSFER_LOOP>
<TRAINING_LOOP_LANES>
<Name>TRAINING_LOOP_LANES</Name>
<TripCount>450</TripCount>
<Latency>460</Latency>
<PipelineII>1</PipelineII>
<PipelineDepth>12</PipelineDepth>
</TRAINING_LOOP_LANES>
<LANES_INSERTION_SORT_OUTER>
<Name>LANES_INSERTION_SORT_OUTER</Name>
<TripCount>6</TripCount>
<Latency>6</Latency>
<PipelineII>1</PipelineII>
<PipelineDepth>2</PipelineDepth>
</LANES_INSERTION_SORT_OUTER>
</SummaryOfLoopLatency>
</PerformanceEstimates>
<AreaEstimates>
<Resources>
<BRAM_18K>8</BRAM_18K>
<DSP48E>1</DSP48E>
<FF>2790</FF>
<LUT>4451</LUT>
<URAM>0</URAM>
</Resources>
</AreaEstimates>
<InterfaceSummary>
<RtlPorts>
<name>ap_clk</name>
<Object>update_knn9</Object>
<Type>return value</Type>
<Scope></Scope>
<IOProtocol>ap_ctrl_hs</IOProtocol>
<IOConfig></IOConfig>
<Dir>in</Dir>
<Bits>1</Bits>
<Attribute>control</Attribute>
</RtlPorts>
<RtlPorts>
<name>ap_rst</name>
<Object>update_knn9</Object>
<Type>return value</Type>
<Scope></Scope>
<IOProtocol>ap_ctrl_hs</IOProtocol>
<IOConfig></IOConfig>
<Dir>in</Dir>
<Bits>1</Bits>
<Attribute>control</Attribute>
</RtlPorts>
<RtlPorts>
<name>ap_start</name>
<Object>update_knn9</Object>
<Type>return value</Type>
<Scope></Scope>
<IOProtocol>ap_ctrl_hs</IOProtocol>
<IOConfig></IOConfig>
<Dir>in</Dir>
<Bits>1</Bits>
<Attribute>control</Attribute>
</RtlPorts>
<RtlPorts>
<name>start_full_n</name>
<Object>update_knn9</Object>
<Type>return value</Type>
<Scope></Scope>
<IOProtocol>ap_ctrl_hs</IOProtocol>
<IOConfig></IOConfig>
<Dir>in</Dir>
<Bits>1</Bits>
<Attribute>unknown</Attribute>
</RtlPorts>
<RtlPorts>
<name>ap_done</name>
<Object>update_knn9</Object>
<Type>return value</Type>
<Scope></Scope>
<IOProtocol>ap_ctrl_hs</IOProtocol>
<IOConfig></IOConfig>
<Dir>out</Dir>
<Bits>1</Bits>
<Attribute>control</Attribute>
</RtlPorts>
<RtlPorts>
<name>ap_continue</name>
<Object>update_knn9</Object>
<Type>return value</Type>
<Scope></Scope>
<IOProtocol>ap_ctrl_hs</IOProtocol>
<IOConfig></IOConfig>
<Dir>in</Dir>
<Bits>1</Bits>
<Attribute>control</Attribute>
</RtlPorts>
<RtlPorts>
<name>ap_idle</name>
<Object>update_knn9</Object>
<Type>return value</Type>
<Scope></Scope>
<IOProtocol>ap_ctrl_hs</IOProtocol>
<IOConfig></IOConfig>
<Dir>out</Dir>
<Bits>1</Bits>
<Attribute>control</Attribute>
</RtlPorts>
<RtlPorts>
<name>ap_ready</name>
<Object>update_knn9</Object>
<Type>return value</Type>
<Scope></Scope>
<IOProtocol>ap_ctrl_hs</IOProtocol>
<IOConfig></IOConfig>
<Dir>out</Dir>
<Bits>1</Bits>
<Attribute>control</Attribute>
</RtlPorts>
<RtlPorts>
<name>start_out</name>
<Object>update_knn9</Object>
<Type>return value</Type>
<Scope></Scope>
<IOProtocol>ap_ctrl_hs</IOProtocol>
<IOConfig></IOConfig>
<Dir>out</Dir>
<Bits>1</Bits>
<Attribute>unknown</Attribute>
</RtlPorts>
<RtlPorts>
<name>start_write</name>
<Object>update_knn9</Object>
<Type>return value</Type>
<Scope></Scope>
<IOProtocol>ap_ctrl_hs</IOProtocol>
<IOConfig></IOConfig>
<Dir>out</Dir>
<Bits>1</Bits>
<Attribute>unknown</Attribute>
</RtlPorts>
<RtlPorts>
<name>Input_1_V_V_dout</name>
<Object>Input_1_V_V</Object>
<Type>pointer</Type>
<Scope></Scope>
<IOProtocol>ap_fifo</IOProtocol>
<IOConfig></IOConfig>
<Dir>in</Dir>
<Bits>32</Bits>
<Attribute>control</Attribute>
</RtlPorts>
<RtlPorts>
<name>Input_1_V_V_empty_n</name>
<Object>Input_1_V_V</Object>
<Type>pointer</Type>
<Scope></Scope>
<IOProtocol>ap_fifo</IOProtocol>
<IOConfig></IOConfig>
<Dir>in</Dir>
<Bits>1</Bits>
<Attribute>control</Attribute>
</RtlPorts>
<RtlPorts>
<name>Input_1_V_V_read</name>
<Object>Input_1_V_V</Object>
<Type>pointer</Type>
<Scope></Scope>
<IOProtocol>ap_fifo</IOProtocol>
<IOConfig></IOConfig>
<Dir>out</Dir>
<Bits>1</Bits>
<Attribute>control</Attribute>
</RtlPorts>
<RtlPorts>
<name>Output_1_V_V_din</name>
<Object>Output_1_V_V</Object>
<Type>pointer</Type>
<Scope></Scope>
<IOProtocol>ap_fifo</IOProtocol>
<IOConfig></IOConfig>
<Dir>out</Dir>
<Bits>32</Bits>
<Attribute>control</Attribute>
</RtlPorts>
<RtlPorts>
<name>Output_1_V_V_full_n</name>
<Object>Output_1_V_V</Object>
<Type>pointer</Type>
<Scope></Scope>
<IOProtocol>ap_fifo</IOProtocol>
<IOConfig></IOConfig>
<Dir>in</Dir>
<Bits>1</Bits>
<Attribute>control</Attribute>
</RtlPorts>
<RtlPorts>
<name>Output_1_V_V_write</name>
<Object>Output_1_V_V</Object>
<Type>pointer</Type>
<Scope></Scope>
<IOProtocol>ap_fifo</IOProtocol>
<IOConfig></IOConfig>
<Dir>out</Dir>
<Bits>1</Bits>
<Attribute>control</Attribute>
</RtlPorts>
</InterfaceSummary>
</Module>
<Module>
<Name>update_knn10</Name>
<PerformanceEstimates>
<SummaryOfTimingAnalysis>
<TargetClockPeriod>10.00</TargetClockPeriod>
<ClockUncertainty>1.25</ClockUncertainty>
<EstimatedClockPeriod>8.677</EstimatedClockPeriod>
</SummaryOfTimingAnalysis>
<SummaryOfOverallLatency>
<Best-caseLatency>494</Best-caseLatency>
<Average-caseLatency>20296</Average-caseLatency>
<Worst-caseLatency>40098</Worst-caseLatency>
<Best-caseRealTimeLatency>4.940 us</Best-caseRealTimeLatency>
<Average-caseRealTimeLatency>0.203 ms</Average-caseRealTimeLatency>
<Worst-caseRealTimeLatency>0.401 ms</Worst-caseRealTimeLatency>
<PipelineInitiationInterval>494 ~ 40098</PipelineInitiationInterval>
<PipelineType>none</PipelineType>
</SummaryOfOverallLatency>
<SummaryOfLoopLatency>
<STORE_LOCAL>
<Name>STORE_LOCAL</Name>
<TripCount>450</TripCount>
<Latency>3600</Latency>
<PipelineII>8</PipelineII>
<PipelineDepth>9</PipelineDepth>
</STORE_LOCAL>
<TRANSFER_LOOP>
<Name>TRANSFER_LOOP</Name>
<TripCount>4500</TripCount>
<Latency>36001</Latency>
<PipelineII>8</PipelineII>
<PipelineDepth>10</PipelineDepth>
</TRANSFER_LOOP>
<TRAINING_LOOP_LANES>
<Name>TRAINING_LOOP_LANES</Name>
<TripCount>450</TripCount>
<Latency>460</Latency>
<PipelineII>1</PipelineII>
<PipelineDepth>12</PipelineDepth>
</TRAINING_LOOP_LANES>
<LANES_INSERTION_SORT_OUTER>
<Name>LANES_INSERTION_SORT_OUTER</Name>
<TripCount>6</TripCount>
<Latency>6</Latency>
<PipelineII>1</PipelineII>
<PipelineDepth>2</PipelineDepth>
</LANES_INSERTION_SORT_OUTER>
</SummaryOfLoopLatency>
</PerformanceEstimates>
<AreaEstimates>
<Resources>
<BRAM_18K>8</BRAM_18K>
<DSP48E>1</DSP48E>
<FF>2791</FF>
<LUT>4482</LUT>
<URAM>0</URAM>
</Resources>
</AreaEstimates>
<InterfaceSummary>
<RtlPorts>
<name>ap_clk</name>
<Object>update_knn10</Object>
<Type>return value</Type>
<Scope></Scope>
<IOProtocol>ap_ctrl_hs</IOProtocol>
<IOConfig></IOConfig>
<Dir>in</Dir>
<Bits>1</Bits>
<Attribute>control</Attribute>
</RtlPorts>
<RtlPorts>
<name>ap_rst</name>
<Object>update_knn10</Object>
<Type>return value</Type>
<Scope></Scope>
<IOProtocol>ap_ctrl_hs</IOProtocol>
<IOConfig></IOConfig>
<Dir>in</Dir>
<Bits>1</Bits>
<Attribute>control</Attribute>
</RtlPorts>
<RtlPorts>
<name>ap_start</name>
<Object>update_knn10</Object>
<Type>return value</Type>
<Scope></Scope>
<IOProtocol>ap_ctrl_hs</IOProtocol>
<IOConfig></IOConfig>
<Dir>in</Dir>
<Bits>1</Bits>
<Attribute>control</Attribute>
</RtlPorts>
<RtlPorts>
<name>ap_done</name>
<Object>update_knn10</Object>
<Type>return value</Type>
<Scope></Scope>
<IOProtocol>ap_ctrl_hs</IOProtocol>
<IOConfig></IOConfig>
<Dir>out</Dir>
<Bits>1</Bits>
<Attribute>control</Attribute>
</RtlPorts>
<RtlPorts>
<name>ap_continue</name>
<Object>update_knn10</Object>
<Type>return value</Type>
<Scope></Scope>
<IOProtocol>ap_ctrl_hs</IOProtocol>
<IOConfig></IOConfig>
<Dir>in</Dir>
<Bits>1</Bits>
<Attribute>control</Attribute>
</RtlPorts>
<RtlPorts>
<name>ap_idle</name>
<Object>update_knn10</Object>
<Type>return value</Type>
<Scope></Scope>
<IOProtocol>ap_ctrl_hs</IOProtocol>
<IOConfig></IOConfig>
<Dir>out</Dir>
<Bits>1</Bits>
<Attribute>control</Attribute>
</RtlPorts>
<RtlPorts>
<name>ap_ready</name>
<Object>update_knn10</Object>
<Type>return value</Type>
<Scope></Scope>
<IOProtocol>ap_ctrl_hs</IOProtocol>
<IOConfig></IOConfig>
<Dir>out</Dir>
<Bits>1</Bits>
<Attribute>control</Attribute>
</RtlPorts>
<RtlPorts>
<name>Input_1_V_V_dout</name>
<Object>Input_1_V_V</Object>
<Type>pointer</Type>
<Scope></Scope>
<IOProtocol>ap_fifo</IOProtocol>
<IOConfig></IOConfig>
<Dir>in</Dir>
<Bits>32</Bits>
<Attribute>control</Attribute>
</RtlPorts>
<RtlPorts>
<name>Input_1_V_V_empty_n</name>
<Object>Input_1_V_V</Object>
<Type>pointer</Type>
<Scope></Scope>
<IOProtocol>ap_fifo</IOProtocol>
<IOConfig></IOConfig>
<Dir>in</Dir>
<Bits>1</Bits>
<Attribute>control</Attribute>
</RtlPorts>
<RtlPorts>
<name>Input_1_V_V_read</name>
<Object>Input_1_V_V</Object>
<Type>pointer</Type>
<Scope></Scope>
<IOProtocol>ap_fifo</IOProtocol>
<IOConfig></IOConfig>
<Dir>out</Dir>
<Bits>1</Bits>
<Attribute>control</Attribute>
</RtlPorts>
<RtlPorts>
<name>Output_1_V_V</name>
<Object>Output_1_V_V</Object>
<Type>pointer</Type>
<Scope></Scope>
<IOProtocol>ap_hs</IOProtocol>
<IOConfig>register</IOConfig>
<Dir>out</Dir>
<Bits>32</Bits>
<Attribute>data</Attribute>
</RtlPorts>
<RtlPorts>
<name>Output_1_V_V_ap_vld</name>
<Object>Output_1_V_V</Object>
<Type>pointer</Type>
<Scope></Scope>
<IOProtocol>ap_hs</IOProtocol>
<IOConfig>register</IOConfig>
<Dir>out</Dir>
<Bits>1</Bits>
<Attribute>control</Attribute>
</RtlPorts>
<RtlPorts>
<name>Output_1_V_V_ap_ack</name>
<Object>Output_1_V_V</Object>
<Type>pointer</Type>
<Scope></Scope>
<IOProtocol>ap_hs</IOProtocol>
<IOConfig>register</IOConfig>
<Dir>in</Dir>
<Bits>1</Bits>
<Attribute>control</Attribute>
</RtlPorts>
</InterfaceSummary>
</Module>
<Module>
<Name>knn_cluster2</Name>
<PerformanceEstimates>
<SummaryOfTimingAnalysis>
<TargetClockPeriod>10.00</TargetClockPeriod>
<ClockUncertainty>1.25</ClockUncertainty>
<EstimatedClockPeriod>8.677</EstimatedClockPeriod>
</SummaryOfTimingAnalysis>
<SummaryOfOverallLatency>
<Best-caseLatency>166134</Best-caseLatency>
<Average-caseLatency>185936</Average-caseLatency>
<Worst-caseLatency>205738</Worst-caseLatency>
<Best-caseRealTimeLatency>1.661 ms</Best-caseRealTimeLatency>
<Average-caseRealTimeLatency>1.859 ms</Average-caseRealTimeLatency>
<Worst-caseRealTimeLatency>2.057 ms</Worst-caseRealTimeLatency>
<DataflowPipelineThroughput>
<range>
<min>495</min>
<max>54497</max>
</range>
</DataflowPipelineThroughput>
<PipelineInitiationInterval>495 ~ 54497</PipelineInitiationInterval>
<PipelineType>dataflow</PipelineType>
</SummaryOfOverallLatency>
</PerformanceEstimates>
<AreaEstimates>
<Resources>
<BRAM_18K>48</BRAM_18K>
<DSP48E>5</DSP48E>
<FF>14212</FF>
<LUT>22687</LUT>
<URAM>0</URAM>
</Resources>
</AreaEstimates>
<InterfaceSummary>
<RtlPorts>
<name>Input_1_V_V</name>
<Object>Input_1_V_V</Object>
<Type>pointer</Type>
<Scope></Scope>
<IOProtocol>ap_hs</IOProtocol>
<IOConfig></IOConfig>
<Dir>in</Dir>
<Bits>32</Bits>
<Attribute>data</Attribute>
<CType>int</CType>
</RtlPorts>
<RtlPorts>
<name>Input_1_V_V_ap_vld</name>
<Object>Input_1_V_V</Object>
<Type>pointer</Type>
<Scope></Scope>
<IOProtocol>ap_hs</IOProtocol>
<IOConfig></IOConfig>
<Dir>in</Dir>
<Bits>1</Bits>
<Attribute>control</Attribute>
<CType>int</CType>
</RtlPorts>
<RtlPorts>
<name>Input_1_V_V_ap_ack</name>
<Object>Input_1_V_V</Object>
<Type>pointer</Type>
<Scope></Scope>
<IOProtocol>ap_hs</IOProtocol>
<IOConfig></IOConfig>
<Dir>out</Dir>
<Bits>1</Bits>
<Attribute>control</Attribute>
<CType>int</CType>
</RtlPorts>
<RtlPorts>
<name>Output_1_V_V</name>
<Object>Output_1_V_V</Object>
<Type>pointer</Type>
<Scope></Scope>
<IOProtocol>ap_hs</IOProtocol>
<IOConfig></IOConfig>
<Dir>out</Dir>
<Bits>32</Bits>
<Attribute>data</Attribute>
<CType>int</CType>
</RtlPorts>
<RtlPorts>
<name>Output_1_V_V_ap_vld</name>
<Object>Output_1_V_V</Object>
<Type>pointer</Type>
<Scope></Scope>
<IOProtocol>ap_hs</IOProtocol>
<IOConfig></IOConfig>
<Dir>out</Dir>
<Bits>1</Bits>
<Attribute>control</Attribute>
<CType>int</CType>
</RtlPorts>
<RtlPorts>
<name>Output_1_V_V_ap_ack</name>
<Object>Output_1_V_V</Object>
<Type>pointer</Type>
<Scope></Scope>
<IOProtocol>ap_hs</IOProtocol>
<IOConfig></IOConfig>
<Dir>in</Dir>
<Bits>1</Bits>
<Attribute>control</Attribute>
<CType>int</CType>
</RtlPorts>
<RtlPorts>
<name>ap_clk</name>
<Object>knn_cluster2</Object>
<Type>return value</Type>
<Scope></Scope>
<IOProtocol>ap_ctrl_hs</IOProtocol>
<IOConfig></IOConfig>
<Dir>in</Dir>
<Bits>1</Bits>
<Attribute>control</Attribute>
</RtlPorts>
<RtlPorts>
<name>ap_rst</name>
<Object>knn_cluster2</Object>
<Type>return value</Type>
<Scope></Scope>
<IOProtocol>ap_ctrl_hs</IOProtocol>
<IOConfig></IOConfig>
<Dir>in</Dir>
<Bits>1</Bits>
<Attribute>control</Attribute>
</RtlPorts>
<RtlPorts>
<name>ap_start</name>
<Object>knn_cluster2</Object>
<Type>return value</Type>
<Scope></Scope>
<IOProtocol>ap_ctrl_hs</IOProtocol>
<IOConfig></IOConfig>
<Dir>in</Dir>
<Bits>1</Bits>
<Attribute>control</Attribute>
</RtlPorts>
<RtlPorts>
<name>ap_done</name>
<Object>knn_cluster2</Object>
<Type>return value</Type>
<Scope></Scope>
<IOProtocol>ap_ctrl_hs</IOProtocol>
<IOConfig></IOConfig>
<Dir>out</Dir>
<Bits>1</Bits>
<Attribute>control</Attribute>
</RtlPorts>
<RtlPorts>
<name>ap_ready</name>
<Object>knn_cluster2</Object>
<Type>return value</Type>
<Scope></Scope>
<IOProtocol>ap_ctrl_hs</IOProtocol>
<IOConfig></IOConfig>
<Dir>out</Dir>
<Bits>1</Bits>
<Attribute>control</Attribute>
</RtlPorts>
<RtlPorts>
<name>ap_idle</name>
<Object>knn_cluster2</Object>
<Type>return value</Type>
<Scope></Scope>
<IOProtocol>ap_ctrl_hs</IOProtocol>
<IOConfig></IOConfig>
<Dir>out</Dir>
<Bits>1</Bits>
<Attribute>control</Attribute>
</RtlPorts>
</InterfaceSummary>
</Module>
</ModuleInformation>

</profile>
